lolapifr/.env
lolapifr/__init__.py
lolapifr/main.py
lolapifr/serveur.py
lolapifr-0.0.5.dist-info/METADATA
lolapifr-0.0.5.dist-info/WHEEL
lolapifr-0.0.5.dist-info/top_level.txt
lolapifr-0.0.5.dist-info/RECORD
