Metadata-Version: 2.1
Name: lolapifr
Version: 0.0.5
Summary: API de League of Legends en français
Author: Manolo
Author-email: emmanuelardoin@gmail.com
Requires-Dist: requests (>2.28.0)
Requires-Dist: python-dotenv (>0.21.0)
